{
  "name": "中央大陸",
  "initialFood": 1500,
  "playerStatusPosition": [ Vector2(-9, 3.8), Vector2(9, 3.8), Vector2(-9, -3.8), Vector2(9, -3.8) ],
  "tablePosition": Vector2(0,0),
  "mas": [
    {"type": "start","position": Vector2(0,2.5)},
    {"type": "land","name":"のら","position": Vector2(2,2.5),"value": 150,"attribute":["center","none"]},
    {"type": "land","name":"いあ","position": Vector2(3.6,1.3),"value": 170,"attribute":["center","none"]},
    {"type": "land","name":"いわん","position": Vector2(5.5,1.8),"value": 400,"attribute":["east","waterside"]},
    {"type": "land","name":"いつう","position": Vector2(7.5,1.8),"value": 420,"attribute":["east","waterside"]},
    {"type": "land","name":"いすりい","position": Vector2(9.5,1.8),"value": 440,"attribute":["east","waterside"]},
    {"type": "heart","position": Vector2(9.5,0)},
    {"type": "land","name":"いふぉう","position": Vector2(9.5,-1.8),"value": 460,"attribute":["east","waterside"]},
    {"type": "land","name":"いふぁいぶ","position": Vector2(7.5,-1.8),"value": 480,"attribute":["east","waterside"]},
    {"type": "land","name":"いしくす","position": Vector2(5.5,-1.8),"value": 500,"attribute":["east","waterside"]},
    {"type": "land","name":"いせ","position": Vector2(3.6,0),"value": 190,"attribute":["center","none"]},
    {"type": "land","name":"いだ","position": Vector2(3.6,-1.3),"value": 210,"attribute":["center","none"]},
    {"type": "land","name":"さら","position": Vector2(2,-2.5),"value": 230,"attribute":["center","none"]},
    {"type": "land","name":"さわん","position": Vector2(3,-4),"value": 520,"attribute":["south","waterside"]},
    {"type": "land","name":"さつう","position": Vector2(1,-4),"value": 540,"attribute":["south","waterside"]},
    {"type": "land","name":"さすりい","position": Vector2(-1,-4),"value": 580,"attribute":["south","waterside"]},
    {"type": "land","name":"さふぉう","position": Vector2(-3,-4),"value": 600,"attribute":["south","waterside"]},
    {"type": "god","position": Vector2(0,-2.5)},
    {"type": "land","name":"され","position": Vector2(-2,-2.5),"value": 250,"attribute":["center","none"]},
    {"type": "land","name":"うだ","position": Vector2(-3.6,-1.3),"value": 270,"attribute":["center","none"]},
    {"type": "land","name":"うわん","position": Vector2(-5.5,-1.8),"value": 620,"attribute":["west","waterside"]},
    {"type": "land","name":"うつう","position": Vector2(-7.5,-1.8),"value": 640,"attribute":["west","waterside"]},
    {"type": "land","name":"うすりい","position": Vector2(-9.5,-1.8),"value": 660,"attribute":["west","waterside"]},
    {"type": "bat","position": Vector2(-9.5,0)},
    {"type": "land","name":"うふぉう","position": Vector2(-9.5,1.8),"value": 680,"attribute":["west","waterside"]},
    {"type": "land","name":"うふぁいぶ","position": Vector2(-7.5,1.8),"value": 700,"attribute":["west","waterside"]},
    {"type": "land","name":"うしくす","position": Vector2(-5.5,1.8),"value": 720,"attribute":["west","waterside"]},
    {"type": "land","name":"うせ","position": Vector2(-3.6,0),"value": 290,"attribute":["center","none"]},
    {"type": "land","name":"うあ","position": Vector2(-3.6,1.3),"value": 310,"attribute":["center","none"]},
    {"type": "land","name":"のれ","position": Vector2(-2,2.5),"value": 330,"attribute":["center","none"]},
    {"type": "land","name":"のわん","position": Vector2(-3,4),"value": 740,"attribute":["north","waterside"]},
    {"type": "land","name":"のつう","position": Vector2(-1,4),"value": 760,"attribute":["north","waterside"]},
    {"type": "land","name":"のすりい","position": Vector2(1,4),"value": 780,"attribute":["north","waterside"]},
    {"type": "land","name":"のふぉう","position": Vector2(3,4),"value": 800,"attribute":["north","waterside"]}
  ]
}